odoo8_addon_account_refund_original-8.0.2.1.0-py2.7-nspkg.pth
odoo8_addon_account_refund_original-8.0.2.1.0.dist-info/DESCRIPTION.rst
odoo8_addon_account_refund_original-8.0.2.1.0.dist-info/METADATA
odoo8_addon_account_refund_original-8.0.2.1.0.dist-info/RECORD
odoo8_addon_account_refund_original-8.0.2.1.0.dist-info/WHEEL
odoo8_addon_account_refund_original-8.0.2.1.0.dist-info/metadata.json
odoo8_addon_account_refund_original-8.0.2.1.0.dist-info/namespace_packages.txt
odoo8_addon_account_refund_original-8.0.2.1.0.dist-info/top_level.txt
odoo_addons/account_refund_original/README.rst
odoo_addons/account_refund_original/__init__.py
odoo_addons/account_refund_original/__openerp__.py
odoo_addons/account_refund_original/i18n/account_refund_original.pot
odoo_addons/account_refund_original/i18n/bg.po
odoo_addons/account_refund_original/i18n/ca.po
odoo_addons/account_refund_original/i18n/cs.po
odoo_addons/account_refund_original/i18n/es.po
odoo_addons/account_refund_original/i18n/es_CO.po
odoo_addons/account_refund_original/i18n/es_CR.po
odoo_addons/account_refund_original/i18n/eu.po
odoo_addons/account_refund_original/i18n/fr.po
odoo_addons/account_refund_original/i18n/gl.po
odoo_addons/account_refund_original/i18n/hr.po
odoo_addons/account_refund_original/i18n/nl.po
odoo_addons/account_refund_original/i18n/pl.po
odoo_addons/account_refund_original/i18n/pt.po
odoo_addons/account_refund_original/i18n/pt_BR.po
odoo_addons/account_refund_original/i18n/ru.po
odoo_addons/account_refund_original/i18n/sl.po
odoo_addons/account_refund_original/i18n/sv.po
odoo_addons/account_refund_original/i18n/tr.po
odoo_addons/account_refund_original/i18n/vi.po
odoo_addons/account_refund_original/models/__init__.py
odoo_addons/account_refund_original/models/account_invoice.py
odoo_addons/account_refund_original/tests/__init__.py
odoo_addons/account_refund_original/tests/test_invoice_refund_link.py
odoo_addons/account_refund_original/views/account_invoice_view.xml
