Metadata-Version: 2.0
Name: odoo8-addon-account-refund-original
Version: 8.0.2.1.0
Summary: Relationship refund - origin invoice
Home-page: https://github.com/OCA/l10n-spain
Author: Spanish Localization Team,Tecnativa,Odoo Community Association (OCA)
Author-email: support@odoo-community.org
License: UNKNOWN
Platform: UNKNOWN
Classifier: Programming Language :: Python :: 2.7
Classifier: Framework :: Odoo
Requires-Dist: odoo (<9.0a,>=8.0a)
